spamwatch/__init__.py
spamwatch/client.py
spamwatch/errors.py
spamwatch/types.py
spamwatch-0.3.0.dist-info/LICENSE
spamwatch-0.3.0.dist-info/METADATA
spamwatch-0.3.0.dist-info/WHEEL
spamwatch-0.3.0.dist-info/top_level.txt
spamwatch-0.3.0.dist-info/RECORD
