Metadata-Version: 2.1
Name: spamwatch
Version: 0.3.0
Summary: SpamWatch API Wrapper
Home-page: https://github.com/SpamWatch/spamwatch-py
Author: Simon Schürrle
Author-email: simon@spamwat.ch
License: License :: OSI Approved :: GNU Lesser General Public License v3 (LGPLv3)
Platform: UNKNOWN
Classifier: Development Status :: 4 - Beta
Classifier: Programming Language :: Python :: 3.6
Classifier: Programming Language :: Python :: 3.7
Classifier: Programming Language :: Python :: Implementation :: CPython
Classifier: Typing :: Typed
Requires-Python: >=3.6
Requires-Dist: requests (>=2.20)
